{
  "id": "doubao-C-20260614T184524Z-99a04e4a40",
  "schema_version": "0.2.0",
  "engine": "doubao",
  "engine_model": "doubao-seed-1-6-flash-250615",
  "query": "上海适合拍照的小众咖啡馆推荐",
  "buyer_segment": "C",
  "timestamp": "2026-06-14T18:45:24.802840Z",
  "raw_answer": "以下是上海一些适合拍照的小众咖啡馆推荐，涵盖不同风格，供你参考：\n\n\n### **1. Mstand（愚园路店）**\n- **地址**：愚园路1398号  \n- **特色**：工业风与艺术感结合，店内有大面积水泥墙、金属装置和独特的咖啡杯展示区，空间设计极具现代感，适合拍摄时尚、个性风格照片。  \n\n\n### **2. SomeOthers（富民路店）**\n- **地址**：富民路291号  \n- **特色**：简约日系风格，以白色为主色调，搭配木质家具和绿植，窗边光线柔和，营造出清新自然的氛围，适合拍摄日系小清新照片。  \n\n\n### **3. Moody Green Coffee（愚园路店）**\n- **地址**：愚园路1398号（与Mstand相邻）  \n- **特色**：绿植环绕的咖啡馆，室内外布满绿色植物，清新自然，仿佛置身于森林中，适合拍摄日系治愈风照片。  \n\n\n### **4. Warm Café & Bistro（愚园路店）**\n- **地址**：愚园路1018号  \n- **特色**：复古工业风，红色砖墙搭配木质家具和复古灯具，充满怀旧氛围，适合拍摄复古、文艺风格照片。  \n\n\n### **5. The Cannery（普陀店）**\n- **地址**：莫干山路50号M50创意园内  \n- **特色**：工业风仓库改造，金属管道、红砖、裸露的天花板等元素，充满艺术感，适合拍摄个性、潮流风格照片。  \n\n\n### **6. OPS CAFE（衡山路店）**\n- **地址**：衡山路838号  \n- **特色**：简约北欧风，白色墙面搭配木质家具和绿植，环境舒适静谧，适合拍摄清新、简约风格照片。  \n\n\n### **7. Mstand（安福路店）**\n- **地址**：安福路248号  \n- **特色**：与愚园路店风格类似，空间设计独特，有透明咖啡豆展示区，现代感十足，适合打卡拍照。  \n\n\n### 拍照小贴士**\n- 提前了解各店的营业时间和人流情况，避开高峰时段拍摄效果更佳；  \n- 根据咖啡馆风格搭配相应服饰，如日系风可选浅色简约穿搭，工业风可尝试牛仔、工装风。\n\n这些小众咖啡馆既有独特的环境设计，又能拍出风格各异的美照，快去打卡吧！",
  "raw_capture_path": "evidence/raw/doubao-C-20260614T184524Z-99a04e4a40.json",
  "screenshot_path": null,
  "is_mock": false,
  "named_brands": [
    "愚园路",
    "M50创意园",
    "衡山路",
    "安福路"
  ],
  "cited_sources": [],
  "product_cards": [],
  "links": [],
  "sentiment": "unscored",
  "request_params": {
    "endpoint": "https://ark.cn-beijing.volces.com/api/v3/chat/completions",
    "model": "doubao-seed-1-6-flash-250615",
    "attempt": 1
  },
  "parser_version": "0.2.0"
}